grab/__init__.py
grab/base.py
grab/cookie.py
grab/deprecated.py
grab/document.py
grab/error.py
grab/proxylist.py
grab/response.py
grab/stat.py
grab/unset.py
grab/upload.py
grab/script/__init__.py
grab/script/crawl.py
grab/spider/__init__.py
grab/spider/base.py
grab/spider/base_service.py
grab/spider/cache_service.py
grab/spider/data.py
grab/spider/decorators.py
grab/spider/error.py
grab/spider/http_api_service.py
grab/spider/parser_service.py
grab/spider/task.py
grab/spider/task_dispatcher_service.py
grab/spider/task_generator_service.py
grab/spider/cache_backend/__init__.py
grab/spider/cache_backend/mongodb.py
grab/spider/cache_backend/mysql.py
grab/spider/cache_backend/postgresql.py
grab/spider/network_service/__init__.py
grab/spider/network_service/multicurl.py
grab/spider/network_service/threaded.py
grab/spider/queue_backend/__init__.py
grab/spider/queue_backend/base.py
grab/spider/queue_backend/memory_queue.py
grab/spider/queue_backend/mongodb_queue.py
grab/spider/queue_backend/redis_queue.py
grab/spider/static/http_api.html
grab/transport/__init__.py
grab/transport/base.py
grab/transport/curl.py
grab/transport/urllib3.py
grab/util/__init__.py
grab/util/config.py
grab/util/default_config.py
grab/util/encoding.py
grab/util/etree.py
grab/util/files.py
grab/util/html.py
grab/util/http.py
grab/util/log.py
grab/util/metric.py
grab/util/misc.py
grab/util/module.py
grab/util/rex.py
grab/util/text.py
grab/util/warning.py
grab-1.2.0.dist-info/licenses/LICENSE
grab-1.2.0.dist-info/METADATA
grab-1.2.0.dist-info/WHEEL
grab-1.2.0.dist-info/top_level.txt
grab-1.2.0.dist-info/RECORD
