Metadata-Version: 2.4
Name: grab
Version: 1.2.0
Summary: Web scraping framework
Author-email: Gregory Petukhov <lorien@lorien.name>
License-Expression: MIT
Project-URL: homepage, http://github.com/lorien/grab
Keywords: pycurl,multicurl,curl,network,parsing,grabbing,scraping
Classifier: Development Status :: 4 - Beta
Classifier: Intended Audience :: Developers
Classifier: Operating System :: OS Independent
Classifier: Programming Language :: Python
Classifier: Programming Language :: Python :: 2
Classifier: Programming Language :: Python :: 2.7
Classifier: Programming Language :: Python :: 3
Classifier: Programming Language :: Python :: 3.0
Classifier: Programming Language :: Python :: 3.1
Classifier: Programming Language :: Python :: 3.10
Classifier: Programming Language :: Python :: 3.11
Classifier: Programming Language :: Python :: 3.12
Classifier: Programming Language :: Python :: 3.13
Classifier: Programming Language :: Python :: 3.2
Classifier: Programming Language :: Python :: 3.3
Classifier: Programming Language :: Python :: 3.4
Classifier: Programming Language :: Python :: 3.5
Classifier: Programming Language :: Python :: 3.6
Classifier: Programming Language :: Python :: 3.7
Classifier: Programming Language :: Python :: 3.8
Classifier: Programming Language :: Python :: 3.9
Classifier: Programming Language :: Python :: Implementation :: CPython
Classifier: Topic :: Internet :: WWW/HTTP
Classifier: Topic :: Software Development :: Libraries :: Application Frameworks
Classifier: Topic :: Software Development :: Libraries :: Python Modules
Requires-Python: >=2.7
License-File: LICENSE
Requires-Dist: six
Requires-Dist: user_agent
Requires-Dist: selection>=2.0.1
Requires-Dist: lxml; platform_system != "Windows" or python_version >= "3.13"
Requires-Dist: pycurl; platform_system != "Windows" or python_version >= "3.13"
Requires-Dist: defusedxml
Requires-Dist: typing-extensions; python_version <= "2.7"
Requires-Dist: unicodec>=0.2.0
Provides-Extra: full
Requires-Dist: urllib3; extra == "full"
Requires-Dist: certifi; extra == "full"
Provides-Extra: urllib3
Requires-Dist: urllib3; extra == "urllib3"
Requires-Dist: certifi; extra == "urllib3"
Provides-Extra: pyquery
Requires-Dist: pyquery; (platform_system != "Windows" and python_version >= "3.0") and extra == "pyquery"
Requires-Dist: pyquery; (platform_system == "Windows" and python_version >= "3.13") and extra == "pyquery"
Requires-Dist: pyquery<=1.4.1; (platform_system != "Windows" and python_version <= "2.7") and extra == "pyquery"
Dynamic: license-file
